{
  "main": {
    "id": "4e712fefb4b9229a",
    "type": "split",
    "children": [
      {
        "id": "f6d0e7dd08f3a9fd",
        "type": "tabs",
        "children": [
          {
            "id": "4a984bd2669d9560",
            "type": "leaf",
            "state": {
              "type": "markdown",
              "state": {
                "file": "src/garden/Shadow DOM-less Web Component library.md",
                "mode": "source",
                "backlinks": false,
                "source": false
              }
            }
          }
        ],
        "stacked": true
      }
    ],
    "direction": "vertical"
  },
  "left": {
    "id": "c021613b76a2f9d9",
    "type": "split",
    "children": [
      {
        "id": "70e732cbc5e6cf0a",
        "type": "tabs",
        "children": [
          {
            "id": "0fe22ccfefd19f6a",
            "type": "leaf",
            "state": {
              "type": "file-explorer",
              "state": {
                "sortOrder": "alphabetical"
              }
            }
          },
          {
            "id": "80e202d18d0f953b",
            "type": "leaf",
            "state": {
              "type": "search",
              "state": {
                "query": "",
                "matchingCase": false,
                "explainSearch": false,
                "collapseAll": false,
                "extraContext": false,
                "sortOrder": "alphabetical"
              }
            }
          }
        ]
      }
    ],
    "direction": "horizontal",
    "width": 231.5
  },
  "right": {
    "id": "84b304f5dd126125",
    "type": "split",
    "children": [
      {
        "id": "1d6099cfd0fb2889",
        "type": "tabs",
        "children": [
          {
            "id": "406535350840703b",
            "type": "leaf",
            "state": {
              "type": "tag",
              "state": {
                "sortOrder": "frequency",
                "useHierarchy": true
              }
            }
          },
          {
            "id": "185612779993f727",
            "type": "leaf",
            "state": {
              "type": "outline",
              "state": {
                "file": "src/garden/Shadow DOM-less Web Component library.md"
              }
            }
          },
          {
            "id": "fa830d8894ba351b",
            "type": "leaf",
            "state": {
              "type": "backlink",
              "state": {
                "file": "src/garden/Shadow DOM-less Web Component library.md",
                "collapseAll": false,
                "extraContext": false,
                "sortOrder": "alphabetical",
                "showSearch": false,
                "searchQuery": "",
                "backlinkCollapsed": false,
                "unlinkedCollapsed": true
              }
            }
          }
        ],
        "currentTab": 1
      }
    ],
    "direction": "horizontal",
    "width": 300,
    "collapsed": true
  },
  "ribbon": {
    "mostRecentAction": ""
  },
  "active": "4a984bd2669d9560",
  "lastOpenFiles": [
    "src/bookmarks/I Can’t Breathe- HeydonWorks.md",
    "src/garden/Shadow DOM-less Web Component library.md",
    "src/bookmarks/Components are pure overhead.md",
    "src/bookmarks/State of Web Components August 2022.md",
    "src/bookmarks/Zero to 60 in Software Development.md",
    "src/bookmarks/Why most design systems implode.md",
    "src/bookmarks/The Patchability of the Open Web.md",
    "src/bookmarks/On Using Web Component Libraries.md",
    "src/bookmarks/My therapist suggested I talk to my inner child. I thought she was joking - but it changed everything.md",
    "src/bookmarks/Into the Personal-Website-Verse.md"
  ]
}