[
  {
    "src": "/../assets/img/badges/badge124.webp",
    "alt": "eyestraining queerness."
  },
  {
    "src": "/../assets/img/badges/badge123.webp",
    "alt": "Best viewed with any browser, 0.0."
  },
  {
    "src": "/../assets/img/badges/badge118.webp",
    "alt": "Anarchy now!"
  },
  {
    "src": "/../assets/img/badges/badge120.webp",
    "alt": "want kibbles…"
  },
  {
    "src": "/../assets/img/badges/badge122.webp",
    "alt": "i ate your cell phone."
  },
  {
    "src": "/../assets/img/badges/badge119.webp",
    "alt": "terfs eat my fat nuts!!!!!!!!!!!!!!!!!!!!!"
  },
  {
    "src": "/../assets/img/badges/badge112.webp",
    "alt": "Bare Minimum JavaScript used.",
    "width": 88,
    "height": 31
  },
  {
    "src": "/../assets/img/badges/badge117.webp",
    "alt": "Graphic design is my passion."
  },
  {
    "src": "/../assets/img/badges/badge116.webp",
    "alt": "Powered by the void."
  },
  {
    "src": "/../assets/img/badges/badge113.webp",
    "alt": "<HTML> learn it today!",
    "href": "https://developer.mozilla.org/en-US/docs/Learn/HTML/Introduction_to_HTML/Getting_started"
  },
  {
    "src": "/../assets/img/badges/badge110.webp",
    "alt": "Certified cringeworthy."
  },
  {
    "src": "/../assets/img/badges/badge115.webp",
    "alt": "Follow me on Bluesky.",
    "href": "https://bsky.app/profile/elly.lol"
  },
  {
    "src": "/../assets/img/badges/badge114.webp",
    "alt": "Industrial workers of the world."
  },
  {
    "src": "/../assets/img/badges/badge111.webp",
    "alt": "queer <coded>."
  },
  {
    "src": "/../assets/img/badges/badge0.webp",
    "alt": "this website kills fascists.",
    "href": "https://en.wikipedia.org/wiki/This_machine_kills_fascists",
    "width": 88,
    "height": 31
  },
  {
    "src": "/../assets/img/badges/badge109.webp",
    "alt": "Ralsei smocking a blunt."
  },
  {
    "src": "/../assets/img/badges/badge108.webp",
    "alt": "Join the Fediverse.",
    "href": "https://fediverse.info/"
  },
  {
    "src": "/../assets/img/badges/badge107.webp",
    "alt": "I support right to repair.",
    "href": "https://www.ifixit.com/Right-to-Repair"
  },
  {
    "src": "/../assets/img/badges/badge105.webp",
    "alt": "Transgendered graphics."
  },
  {
    "src": "/../assets/img/badges/badge106.webp",
    "alt": "IWC Now! IndieWeb.org",
    "href": "https://indieweb.org/"
  },
  {
    "src": "/../assets/img/badges/badge104.webp",
    "alt": "homo."
  },
  {
    "src": "/../assets/img/badges/badge98.webp",
    "alt": "Let's git coding."
  },
  {
    "src": "/../assets/img/badges/badge121.webp",
    "alt": "Best viewed with any browser."
  },
  {
    "src": "/../assets/img/badges/badge102.webp",
    "alt": "Internet Archive. Preserve this internet, games, TV, software, books, photos, history!",
    "href": "https://archive.org/"
  },
  {
    "src": "/../assets/img/badges/badge103.webp",
    "alt": "Lesbian ❤️."
  },
  {
    "src": "/../assets/img/badges/badge101.webp",
    "alt": "made by hand."
  },
  {
    "src": "/../assets/img/badges/badge100.webp",
    "alt": "Burn Internet Explorer."
  },
  {
    "src": "/../assets/img/badges/badge99.webp",
    "alt": "you're telling me a queer coded this."
  },
  {
    "src": "/../assets/img/badges/badge91.webp",
    "alt": "a very excited emoticon shaking it's hands up and down."
  },
  {
    "src": "/../assets/img/badges/badge96.webp",
    "alt": "I ❤️ my brick."
  },
  {
    "src": "/../assets/img/badges/badge97.webp",
    "alt": "fuck nazis."
  },
  {
    "src": "/../assets/img/badges/badge95.webp",
    "alt": "Take back the web.",
    "href": "https://www.mozilla.org/en-US/firefox/new/"
  },
  {
    "src": "/../assets/img/badges/badge94.webp",
    "alt": "I was on Cohost."
  },
  {
    "src": "/../assets/img/badges/badge87.webp",
    "alt": "The cutest little pixel art puppy sleeping soundly."
  },
  {
    "src": "/../assets/img/badges/badge93.webp",
    "alt": "Danger: Dumbass webmaster ahead."
  },
  {
    "src": "/../assets/img/badges/badge92.webp",
    "alt": "Built with Eleventy."
  },
  {
    "src": "/../assets/img/badges/badge125.webp",
    "alt": "bro ur sparkling."
  },
  {
    "src": "/../assets/img/badges/badge89.webp",
    "alt": "cation, I bite."
  },
  {
    "src": "/../assets/img/badges/badge86.webp",
    "alt": "Digital sex."
  },
  {
    "src": "/../assets/img/badges/badge82.webp",
    "alt": "I ❤️ my friends."
  },
  {
    "src": "/../assets/img/badges/badge83.webp",
    "alt": "Made with 11ty."
  },
  {
    "src": "/../assets/img/badges/badge78.webp",
    "alt": "Everyday I wake up."
  },
  {
    "src": "/../assets/img/badges/badge79.webp",
    "alt": "I ❤️ my boobs."
  },
  {
    "src": "/../assets/img/badges/badge77.webp",
    "alt": "I ❤️ my cat."
  },
  {
    "src": "/../assets/img/badges/badge75.webp",
    "alt": "Woof woof woof !!!"
  },
  {
    "src": "/../assets/img/badges/badge72.webp",
    "alt": "JSON valid.",
    "href": "/feed.json"
  },
  {
    "src": "/../assets/img/badges/badge69.webp",
    "alt": "about:blank."
  },
  {
    "src": "/../assets/img/badges/badge68.webp",
    "alt": "Walky walk, pixel dog."
  },
  {
    "src": "/../assets/img/badges/badge65.webp",
    "alt": "RSS Feed."
  },
  {
    "src": "/../assets/img/badges/badge66.webp",
    "alt": "I feel violated by corporate invasion on my attention span.",
    "width": 150,
    "height": 20
  },
  {
    "src": "/../assets/img/badges/badge61.webp",
    "alt": "ACAB."
  },
  {
    "src": "/../assets/img/badges/badge62.webp",
    "alt": "code by hand."
  },
  {
    "src": "/../assets/img/badges/badge60.webp",
    "alt": "believe in the radical power of friendship."
  },
  {
    "src": "/../assets/img/badges/badge58.webp",
    "alt": "CSS is awesome."
  },
  {
    "src": "/../assets/img/badges/badge53.webp",
    "alt": "stick your dick in the dvd slot.",
    "width": 150,
    "height": 20
  },
  {
    "src": "/../assets/img/badges/badge52.webp",
    "alt": "people pledge.",
    "href": "https://people.pledge.party/"
  },
  {
    "src": "/../assets/img/badges/badge51.webp",
    "alt": "Trans ❤️."
  },
  {
    "src": "/../assets/img/badges/badge50.webp",
    "alt": "Follow me on Mastodon.",
    "href": "https://front-end.social/@elly"
  },
  {
    "src": "/../assets/img/badges/badge47.webp",
    "alt": "fuck gender."
  },
  {
    "src": "/../assets/img/badges/badge46.webp",
    "alt": "Made with my own two paws."
  },
  {
    "src": "/../assets/img/badges/badge44.webp",
    "alt": "all browsers."
  },
  {
    "src": "/../assets/img/badges/badge41.webp",
    "alt": "88x31."
  },
  {
    "src": "/../assets/img/badges/badge36.webp",
    "alt": "JS not needed.",
    "width": 88,
    "height": 31
  },
  {
    "src": "/../assets/img/badges/badge90.webp",
    "alt": "Trans rights now!"
  },
  {
    "src": "/../assets/img/badges/badge88.webp",
    "alt": ">. ! <freak>"
  },
  {
    "src": "/../assets/img/badges/badge85.webp",
    "alt": "web standards."
  },
  {
    "src": "/../assets/img/badges/badge84.webp",
    "alt": "go anarchy."
  },
  {
    "src": "/../assets/img/badges/badge80.webp",
    "alt": "I'm not human."
  },
  {
    "src": "/../assets/img/badges/badge81.webp",
    "alt": "I love old web."
  },
  {
    "src": "/../assets/img/badges/badge76.webp",
    "alt": "Anti-JS JS Club.",
    "width": 88,
    "height": 31
  },
  {
    "src": "/../assets/img/badges/badge73.webp",
    "alt": "Webmentions supported.",
    "href": "https://webmentions.neocities.org/"
  },
  {
    "src": "/../assets/img/badges/badge74.webp",
    "alt": "Microformats.",
    "href": "https://microformats.org/"
  },
  {
    "src": "/../assets/img/badges/badge70.webp",
    "alt": "Autism creature."
  },
  {
    "src": "/../assets/img/badges/badge71.webp",
    "alt": "All browsers are beautiful, ABAB."
  },
  {
    "src": "/../assets/img/badges/badge59.webp",
    "alt": "Trans version of the DVD logo bounce."
  },
  {
    "src": "/../assets/img/badges/badge67.webp",
    "alt": "I use Vivaldi.",
    "href": "https://vivaldi.com/"
  },
  {
    "src": "/../assets/img/badges/badge63.webp",
    "alt": "Best pussy disorder!!!"
  },
  {
    "src": "/../assets/img/badges/badge64.webp",
    "alt": "I ❤️ anime."
  },
  {
    "src": "/../assets/img/badges/badge57.webp",
    "alt": "Trans flag."
  },
  {
    "src": "/../assets/img/badges/badge56.webp",
    "alt": "Running mushroom, Delicious in Dungeon."
  },
  {
    "src": "/../assets/img/badges/badge55.webp",
    "alt": "Dykelover."
  },
  {
    "src": "/../assets/img/badges/badge54.webp",
    "alt": "DYI HRT.",
    "href": "https://hrt.coffee/"
  },
  {
    "src": "/../assets/img/badges/badge49.webp",
    "alt": "Slime girl."
  },
  {
    "src": "/../assets/img/badges/badge48.webp",
    "alt": "I ❤️ weirdo women."
  },
  {
    "src": "/../assets/img/badges/badge43.webp",
    "alt": "Fox floof explode."
  },
  {
    "src": "/../assets/img/badges/badge45.webp",
    "alt": "I support key mash equality asdjfikdfsjlkjf."
  },
  {
    "src": "/../assets/img/badges/badge40.webp",
    "alt": "lesbian lap dog."
  },
  {
    "src": "/../assets/img/badges/badge42.webp",
    "alt": "Cock sucking faggot."
  },
  {
    "src": "/../assets/img/badges/badge39.webp",
    "alt": "Dogdyke."
  },
  {
    "src": "/../assets/img/badges/badge38.webp",
    "alt": "This machine kills fascists."
  },
  {
    "src": "/../assets/img/badges/badge37.webp",
    "alt": "ATOM valid.",
    "href": "/feed.atom"
  },
  {
    "src": "/../assets/img/badges/badge33.webp",
    "alt": "You are the 999,999th visitor: Congratulations you won! Click here to claim."
  },
  {
    "src": "/../assets/img/badges/badge35.webp",
    "alt": "This website is gay."
  },
  {
    "src": "/../assets/img/badges/badge29.webp",
    "alt": "Fueled by dyke sweat."
  },
  {
    "src": "/../assets/img/badges/badge34.webp",
    "alt": "Made with Cascading Style Sheets."
  },
  {
    "src": "/../assets/img/badges/badge32.webp",
    "alt": "Responsive website."
  },
  {
    "src": "/../assets/img/badges/badge31.webp",
    "alt": "Valid RSS.",
    "href": "/feed.rss"
  },
  {
    "src": "/../assets/img/badges/badge30.webp",
    "alt": "I need a nap now!"
  },
  {
    "src": "/../assets/img/badges/badge28.webp",
    "alt": "Free Palestine.",
    "href": "https://techforpalestine.org/learn-more/"
  },
  {
    "src": "/../assets/img/badges/badge26.webp",
    "alt": "your non biney?."
  },
  {
    "src": "/../assets/img/badges/badge27.webp",
    "alt": "I dream in HTML."
  },
  {
    "src": "/../assets/img/badges/badge25.webp",
    "alt": "W3C Shit HTML."
  },
  {
    "src": "/../assets/img/badges/badge21.webp",
    "alt": "Catscape, Meow! 2.0"
  },
  {
    "src": "/../assets/img/badges/badge3.webp",
    "alt": "Cringe is dead."
  },
  {
    "src": "/../assets/img/badges/badge4.webp",
    "alt": "Trans your gender."
  },
  {
    "src": "/../assets/img/badges/badge14.webp",
    "alt": "Prone to poor decision when hot dykes are involved."
  },
  {
    "src": "/../assets/img/badges/badge24.webp",
    "alt": "Stand with Palestine."
  },
  {
    "src": "/../assets/img/badges/badge23.webp",
    "alt": "Queer pride ❤️."
  },
  {
    "src": "/../assets/img/badges/badge2.webp",
    "alt": "Google Chrome is evil!"
  },
  {
    "src": "/../assets/img/badges/badge20.webp",
    "alt": "Dykelover."
  },
  {
    "src": "/../assets/img/badges/badge22.webp",
    "alt": "there's no ai here!"
  },
  {
    "src": "/../assets/img/badges/badge9.webp",
    "alt": "Powered by EchoFeed.",
    "href": "https://echofeed.app/",
    "width": 88,
    "height": 31
  },
  {
    "src": "/../assets/img/badges/badge126.webp",
    "alt": "Fuck 31x88."
  },
  {
    "src": "/../assets/img/badges/badge13.webp",
    "alt": "NFT, No Fucking Thanks!"
  },
  {
    "src": "/../assets/img/badges/badge11.webp",
    "alt": "Web design is my passion."
  },
  {
    "src": "/../assets/img/badges/badge7.webp",
    "alt": "I ❤️ girlfags."
  },
  {
    "src": "/../assets/img/badges/badge12.webp",
    "alt": "Delete Chrome!"
  },
  {
    "src": "/../assets/img/badges/badge10.webp",
    "alt": "uBlock Origin now!",
    "href": "https://ublockorigin.com/"
  },
  {
    "src": "/../assets/img/badges/badge6.webp",
    "alt": "made by a girl."
  },
  {
    "src": "/../assets/img/badges/badge15.webp",
    "alt": "Autism!"
  },
  {
    "src": "/../assets/img/badges/badge1.webp",
    "alt": "puppy glitch."
  },
  {
    "src": "/../assets/img/badges/badge8.webp",
    "alt": "Not a person."
  },
  {
    "src": "/../assets/img/badges/badge5.webp",
    "alt": "Ditch social media now!"
  },
  {
    "src": "/../assets/img/badges/badge18.webp",
    "alt": "Toxic yuri."
  },
  {
    "src": "/../assets/img/badges/badge19.webp",
    "alt": "Girls, now! 3.0"
  },
  {
    "src": "/../assets/img/badges/badge17.webp",
    "alt": "Never judge a girl by her blinkie."
  },
  {
    "src": "/../assets/img/badges/badge16.webp",
    "alt": "lesbian dog plushie."
  }
]
